specta/__init__.py
specta/_version.py
specta/addon.py
specta/app_static/build/1127.33a4085.js
specta/app_static/build/114.758c87e.js
specta/app_static/build/1150.429577d.js
specta/app_static/build/1213.ef7e9e9.js
specta/app_static/build/1252.dd3eb53.js
specta/app_static/build/1310.7231328.js
specta/app_static/build/133.9e1383f.js
specta/app_static/build/1344.439b779.js
specta/app_static/build/137.27117e0.js
specta/app_static/build/144.324c58a.js
specta/app_static/build/1445.dea30ca.js
specta/app_static/build/1472.3879cdd.js
specta/app_static/build/1506.295b811.js
specta/app_static/build/1527.ada913c.js
specta/app_static/build/1543.41b7257.js
specta/app_static/build/1543.41b7257.js.LICENSE.txt
specta/app_static/build/156.a1a38db.js
specta/app_static/build/157.66cf241.js
specta/app_static/build/1684.7e40cb4.js
specta/app_static/build/1723.761483b.js
specta/app_static/build/1749.7252fab.js
specta/app_static/build/1842.a769c1e.js
specta/app_static/build/1864.360e131.js
specta/app_static/build/1874.46f54c4.js
specta/app_static/build/1878.0139b60.js
specta/app_static/build/1915.615328c.js
specta/app_static/build/1967.bd0459d.js
specta/app_static/build/1984.a6d5526.js
specta/app_static/build/2040.a1bd2cd.js
specta/app_static/build/2056.acc7537.js
specta/app_static/build/2079.b67f3b7.js
specta/app_static/build/208.022462a.js
specta/app_static/build/2080.a10c54d.js
specta/app_static/build/2108.e89a34c.js
specta/app_static/build/2232.53da194.js
specta/app_static/build/2257.6772e55.js
specta/app_static/build/2341.f3f836b.js
specta/app_static/build/2341.f3f836b.js.LICENSE.txt
specta/app_static/build/2348.4cb72b1.js
specta/app_static/build/2410.09a15da.js
specta/app_static/build/2413.fcb0452.js
specta/app_static/build/2420.b74847f.js
specta/app_static/build/2429.fb72cda.js
specta/app_static/build/243.43b4004.js
specta/app_static/build/2446.2d3f77f.js
specta/app_static/build/2468.d8392d6.js
specta/app_static/build/2515.085e038.js
specta/app_static/build/2571.a62d4ed.js
specta-0.4.7.dist-info/METADATA
specta-0.4.7.dist-info/WHEEL
specta-0.4.7.dist-info/entry_points.txt
specta-0.4.7.dist-info/licenses/LICENSE
specta-0.4.7.dist-info/RECORD
