Metadata-Version: 2.4
Name: specta
Version: 0.4.7
Dynamic: Keywords
Project-URL: Homepage, https://github.com/trungleduc/specta
Project-URL: Bug Tracker, https://github.com/trungleduc/specta/issues
Project-URL: Repository, https://github.com/trungleduc/specta.git
Author-email: Trung Le <leductrungxf@gmail.com>
License: MIT License
License-File: LICENSE
Classifier: Framework :: Jupyter
Classifier: Framework :: Jupyter :: JupyterLab
Classifier: Framework :: Jupyter :: JupyterLab :: 4
Classifier: Framework :: Jupyter :: JupyterLab :: Extensions
Classifier: Framework :: Jupyter :: JupyterLab :: Extensions :: Prebuilt
Classifier: License :: OSI Approved :: BSD License
Classifier: Programming Language :: Python
Classifier: Programming Language :: Python :: 3
Classifier: Programming Language :: Python :: 3.8
Classifier: Programming Language :: Python :: 3.9
Classifier: Programming Language :: Python :: 3.10
Classifier: Programming Language :: Python :: 3.11
Requires-Python: >=3.9
Requires-Dist: jupyterlite-core<0.8,>=0.7.0
